README.md
jupyter-extjs.json
setup.cfg
setup.py
extjs/__init__.py
extjs/_version.py
extjs.egg-info/PKG-INFO
extjs.egg-info/SOURCES.txt
extjs.egg-info/dependency_links.txt
extjs.egg-info/not-zip-safe
extjs.egg-info/requires.txt
extjs.egg-info/top_level.txt
extjs/static/extension.js
extjs/static/Ext/exporter/Base.js
extjs/static/Ext/exporter/Excel.js
extjs/static/Ext/exporter/File.js
extjs/static/Ext/exporter/Plugin.js
extjs/static/Ext/exporter/data/Base.js
extjs/static/Ext/exporter/data/Cell.js
extjs/static/Ext/exporter/data/Column.js
extjs/static/Ext/exporter/data/Group.js
extjs/static/Ext/exporter/data/Row.js
extjs/static/Ext/exporter/data/Table.js
extjs/static/Ext/exporter/file/Base.js
extjs/static/Ext/exporter/file/Style.js
extjs/static/Ext/exporter/file/excel/Cell.js
extjs/static/Ext/exporter/file/excel/Column.js
extjs/static/Ext/exporter/file/excel/Row.js
extjs/static/Ext/exporter/file/excel/Style.js
extjs/static/Ext/exporter/file/excel/Table.js
extjs/static/Ext/exporter/file/excel/Workbook.js
extjs/static/Ext/exporter/file/excel/Worksheet.js
extjs/static/Ext/exporter/text/CSV.js
extjs/static/Ext/grid/plugin/Exporter.js
extjs/static/images/excel.png
extjs/static/jupyter/Engine.js
extjs/static/jupyter/chart/TSChart.js
extjs/static/jupyter/chart/sprite/Line.js
extjs/static/jupyter/store/JupyterProxy.js
extjs/static/jupyter/view/GridPanel.js
extjs/static/jupyter/view/TreeGridPanel.js